sed4onnx/__init__.py
sed4onnx/__main__.py
sed4onnx/onnx_constant_encoder_decoder.py
sed4onnx-1.0.4.dist-info/LICENSE
sed4onnx-1.0.4.dist-info/METADATA
sed4onnx-1.0.4.dist-info/WHEEL
sed4onnx-1.0.4.dist-info/entry_points.txt
sed4onnx-1.0.4.dist-info/top_level.txt
sed4onnx-1.0.4.dist-info/RECORD
