Metadata-Version: 2.1
Name: sed4onnx
Version: 1.0.4
Summary: Simple ONNX constant encoder/decoder.
Home-page: https://github.com/PINTO0309/sed4onnx
Author: Katsuya Hyodo
Author-email: rmsdh122@yahoo.co.jp
License: MIT License
Platform: linux
Platform: unix
Requires-Python: >=3.6
License-File: LICENSE
